CHANGELOG.md
litmnist/__init__.py
litmnist/cli.py
litmnist/core.py
litmnist-0.1.0.dist-info/entry_points.txt
litmnist-0.1.0.dist-info/LICENSE
litmnist-0.1.0.dist-info/WHEEL
litmnist-0.1.0.dist-info/METADATA
litmnist-0.1.0.dist-info/RECORD
