Metadata-Version: 2.1
Name: litmnist
Version: 0.1.0
Summary: PyTorch Lightning demo on the MNIST dataset
Home-page: https://github.com/XavierJiezou/LitMNIST
Keywords: PyTorch,PyTorch-Lightning,MNIST
Author: XavierJiezou
Author-email: 878972272@qq.com
Requires-Python: >=3.7,<4.0
Classifier: Programming Language :: Python :: 3
Classifier: Programming Language :: Python :: 3.10
Classifier: Programming Language :: Python :: 3.7
Classifier: Programming Language :: Python :: 3.8
Classifier: Programming Language :: Python :: 3.9
Classifier: Topic :: Software Development :: Libraries :: Python Modules
Requires-Dist: fire (>=0.4.0,<0.5.0)
Requires-Dist: pytorch-lightning (>=1.6.3,<2.0.0)
Requires-Dist: rich (>=12.3.0,<13.0.0)
Requires-Dist: torch (>=1.11.0,<2.0.0)
Requires-Dist: torchvision (>=0.12.0,<0.13.0)
Project-URL: Documentation, https://github.com/XavierJiezou/LitMNIST
Project-URL: Repository, https://github.com/XavierJiezou/LitMNIST
